<?xml version="1.0" encoding="UTF-8"?>
<!DOCTYPE DjVuXML>
<DjVuXML>
<BODY>
<OBJECT data="file://localhost//var/tmp/autoclean/derive/cinquiemeconvers00unse//cinquiemeconvers00unse.djvu" height="4335" type="image/x.djvu" usemap="cinquiemeconvers00unse_0001.djvu" width="2506">
<PARAM name="PAGE" value="cinquiemeconvers00unse_0001.djvu"/>
<PARAM name="DPI" value="500"/>
<HIDDENTEXT>
<PAGECOLUMN>
<REGION backgroundColor="15328721">
<PARAGRAPH>
<LINE>
<WORD coords="1911,713,2159,655,711">^k«C</WORD>
</LINE>
</PARAGRAPH>
</REGION>
</PAGECOLUMN>
<PAGECOLUMN></PAGECOLUMN>
<PAGECOLUMN>
<REGION backgroundColor="15131597">
<PARAGRAPH>
<LINE>
<WORD coords="269,1013,867,905,986">CINQUIEME</WORD>
<WORD coords="955,1003,1781,909,995">CONVERSATION</WORD>
<WORD coords="1923,1005,2083,927,1002">[IU</WORD>
<WORD coords="2107,1015,2157,945,1015">7</WORD>
</LINE>
</PARAGRAPH>
</REGION>
</PAGECOLUMN>
<PAGECOLUMN>
<REGION backgroundColor="15131598">
<PARAGRAPH>
<LINE>
<WORD coords="219,1185,735,1127,1181">entre</WORD>
</LINE>
</PARAGRAPH>
<PARAGRAPH>
<LINE>
<WORD coords="271,1337,365,1275,1337">M.</WORD>
<WORD coords="423,1341,861,1275,1339">RICHARD</WORD>
<WORD coords="917,1341,1043,1283,1341">ET</WORD>
<WORD coords="1095,1345,1189,1275,1343">M.</WORD>
<WORD coords="1251,1351,1775,1283,1347">COURTOIS.</WORD>
</LINE>
</PARAGRAPH>
<PARAGRAPH>
<LINE>
<WORD coords="811,1511,923,1449,1511">M.</WORD>
<WORD coords="967,1511,1279,1443,1509">Richard.</WORD>
</LINE>
</PARAGRAPH>
<PARAGRAPH>
<LINE>
<WORD coords="239,1785,621,1609,1745">C^u’elle</WORD>
<WORD coords="665,1749,971,1677,1746">nouvelle</WORD>
<WORD coords="1015,1773,1247,1677,1748">depuis</WORD>
<WORD coords="1301,1775,1431,1705,1751">que</WORD>
<WORD coords="1465,1775,1529,1681,1751">je</WORD>
<WORD coords="1569,1753,1691,1683,1753">n’ai</WORD>
<WORD coords="1735,1753,1819,1705,1753">eu</WORD>
</LINE>
<LINE>
<WORD coords="229,1899,293,1827,1898">le</WORD>
<WORD coords="349,1923,561,1829,1900">plaifir</WORD>
<WORD coords="607,1903,693,1831,1903">de</WORD>
<WORD coords="741,1905,907,1857,1904">vous</WORD>
<WORD coords="963,1909,1353,1851,1905">rencontrer</WORD>
<WORD coords="1385,1911,1417,1839,1911">?</WORD>
</LINE>
</PARAGRAPH>
</REGION>
</PAGECOLUMN>
<PAGECOLUMN>
<REGION backgroundColor="15197649">
<PARAGRAPH>
<LINE>
<WORD coords="793,2092,896,2035,2092">M.</WORD>
<WORD coords="947,2096,1241,2034,2094">Courtois</WORD>
<WORD coords="1247,2096,1261,2082,2096">.</WORD>
</LINE>
</PARAGRAPH>
</REGION>
</PAGECOLUMN>
<PAGECOLUMN>
<REGION backgroundColor="15263186">
<PARAGRAPH>
<LINE>
<WORD coords="325,2311,511,2233,2309">Vous</WORD>
<WORD coords="567,2311,663,2241,2309">les</WORD>
<WORD coords="717,2317,899,2239,2313">favez</WORD>
<WORD coords="947,2317,1173,2257,2314">toutes</WORD>
<WORD coords="1225,2319,1359,2247,2318">fans</WORD>
<WORD coords="1401,2319,1613,2247,2319">doute</WORD>
<WORD coords="1663,2323,1821,2249,2321">auffî</WORD>
</LINE>
<LINE>
<WORD coords="229,2473,383,2395,2470">bien</WORD>
<WORD coords="415,2495,545,2425,2471">que</WORD>
<WORD coords="589,2493,771,2405,2471">moi;</WORD>
<WORD coords="817,2497,963,2429,2475">car,</WORD>
<WORD coords="1007,2477,1181,2407,2477">Dieu</WORD>
<WORD coords="1205,2501,1447,2413,2478">merci,</WORD>
<WORD coords="1485,2481,1595,2435,2481">ces</WORD>
<WORD coords="1639,2483,1825,2409,2481">Mef-</WORD>
</LINE>
<LINE>
<WORD coords="229,2631,429,2559,2629">fieurs</WORD>
<WORD coords="481,2629,543,2561,2629">le</WORD>
<WORD coords="609,2631,751,2561,2630">font</WORD>
<WORD coords="811,2635,1155,2565,2633">tellement</WORD>
<WORD coords="1205,2641,1603,2567,2638">découverts</WORD>
<WORD coords="1647,2641,1821,2589,2639">eux-</WORD>
</LINE>
<LINE>
<WORD coords="233,2791,485,2721,2789">mêmes</WORD>
<WORD coords="509,2811,527,2775,2813">,</WORD>
<WORD coords="589,2815,771,2721,2791">qu’ils</WORD>
<WORD coords="805,2795,1011,2721,2793">m’ont</WORD>
<WORD coords="1053,2799,1235,2725,2796">évité</WORD>
<WORD coords="1277,2799,1315,2725,2800">à</WORD>
<WORD coords="1347,2801,1483,2733,2799">moi</WORD>
<WORD coords="1523,2801,1585,2729,2800">la</WORD>
<WORD coords="1625,2825,1823,2731,2801">peine</WORD>
</LINE>
<LINE>
<WORD coords="247,2947,337,2875,2947">de</WORD>
<WORD coords="375,2949,471,2877,2947">les</WORD>
<WORD coords="517,2977,919,2877,2949">démafquer.</WORD>
</LINE>
</PARAGRAPH>
<PARAGRAPH>
<LINE>
<WORD coords="795,3161,899,3101,3159">M.</WORD>
<WORD coords="947,3165,1251,3101,3162">Richard.</WORD>
</LINE>
</PARAGRAPH>
<PARAGRAPH>
<LINE>
<WORD coords="325,3379,543,3285,3357">Quoi!</WORD>
<WORD coords="605,3361,765,3315,3360">vous</WORD>
<WORD coords="807,3363,889,3317,3362">en</WORD>
<WORD coords="937,3365,1221,3317,3362">revenez</WORD>
<WORD coords="1271,3389,1569,3299,3365">toujours</WORD>
<WORD coords="1611,3369,1649,3295,3370">à</WORD>
<WORD coords="1703,3371,1821,3321,3369">vos</WORD>
</LINE>
<LINE>
<WORD coords="235,3517,399,3445,3516">bons</WORD>
<WORD coords="447,3519,607,3451,3518">amis</WORD>
<WORD coords="661,3521,759,3447,3520">les</WORD>
<WORD coords="821,3545,1165,3451,3522">Jacobins,</WORD>
<WORD coords="1235,3525,1309,3451,3526">&amp;</WORD>
<WORD coords="1357,3527,1521,3479,3524">vous</WORD>
<WORD coords="1577,3555,1819,3479,3526">croyez</WORD>
</LINE>
</PARAGRAPH>
</REGION>
</PAGECOLUMN>
<PAGECOLUMN>
<REGION backgroundColor="15328722">
<PARAGRAPH>
<LINE>
<WORD coords="1273,3852,1347,3781,3852">M</WORD>
<WORD coords="1377,3851,1427,3785,3851">h</WORD>
<WORD coords="1479,3843,1547,3777,3842">uJ</WORD>
<WORD coords="1619,3845,1745,3773,3846">33</WORD>
<WORD coords="1873,3851,1919,3765,3851">y</WORD>
</LINE>
</PARAGRAPH>
</REGION>
</PAGECOLUMN>
</HIDDENTEXT>
</OBJECT>
<MAP name="cinquiemeconvers00unse_0001.djvu"/>
<OBJECT data="file://localhost//var/tmp/autoclean/derive/cinquiemeconvers00unse//cinquiemeconvers00unse.djvu" height="4335" type="image/x.djvu" usemap="cinquiemeconvers00unse_0002.djvu" width="2506">
<PARAM name="PAGE" value="cinquiemeconvers00unse_0002.djvu"/>
<PARAM name="DPI" value="500"/>
<HIDDENTEXT>
<PAGECOLUMN>
<REGION backgroundColor="15264214">
<PARAGRAPH>
<LINE>
<WORD coords="1443,641,1653,539,637">c*;</WORD>
</LINE>
</PARAGRAPH>
<PARAGRAPH>
<LINE>
<WORD coords="744,807,876,734,780">que</WORD>
<WORD coords="918,781,995,735,780">ce</WORD>
<WORD coords="1038,782,1177,710,780">font</WORD>
<WORD coords="1231,784,1357,735,782">eux</WORD>
<WORD coords="1406,809,1522,715,780">qui</WORD>
<WORD coords="1577,785,1739,739,784">nous</WORD>
<WORD coords="1782,786,1898,728,784">ont</WORD>
<WORD coords="1950,790,2135,718,786">caufé</WORD>
<WORD coords="2195,789,2347,730,788">tout</WORD>
</LINE>
<LINE>
<WORD coords="746,940,807,871,939">le</WORD>
<WORD coords="861,966,1095,878,941">tapage</WORD>
<WORD coords="1154,941,1238,870,940">de</WORD>
<WORD coords="1283,944,1346,874,943">la</WORD>
<WORD coords="1403,945,1683,875,943">femaine</WORD>
<WORD coords="1735,948,2054,874,946">dernière.</WORD>
</LINE>
</PARAGRAPH>
<PARAGRAPH>
<LINE>
<WORD coords="1315,1156,1417,1097,1156">M.</WORD>
<WORD coords="1463,1159,1742,1098,1157">Courtois</WORD>
<WORD coords="1748,1157,1761,1144,1157">.</WORD>
</LINE>
</PARAGRAPH>
<PARAGRAPH>
<LINE>
<WORD coords="837,1376,985,1302,1375">Oh!</WORD>
<WORD coords="1045,1400,1215,1330,1375">pour</WORD>
<WORD coords="1288,1393,1597,1304,1374">celui-là,</WORD>
<WORD coords="1665,1377,1760,1308,1375">les</WORD>
<WORD coords="1826,1379,2129,1307,1377">Jacobins</WORD>
<WORD coords="2188,1378,2347,1306,1377">l’ont</WORD>
</LINE>
<LINE>
<WORD coords="741,1561,1080,1468,1536">approuvé</WORD>
<WORD coords="1114,1561,1335,1465,1533">quand</WORD>
<WORD coords="1377,1534,1420,1468,1533">il</WORD>
<WORD coords="1448,1536,1484,1491,1536">a</WORD>
<WORD coords="1523,1536,1633,1466,1535">été</WORD>
<WORD coords="1677,1557,1833,1465,1534">fait;</WORD>
<WORD coords="1879,1536,2039,1469,1534">mais</WORD>
<WORD coords="2072,1535,2151,1467,1533">ils</WORD>
<WORD coords="2183,1536,2337,1465,1535">n’en</WORD>
</LINE>
<LINE>
<WORD coords="740,1697,883,1627,1696">font</WORD>
<WORD coords="930,1719,1041,1652,1695">pas</WORD>
<WORD coords="1081,1694,1173,1627,1693">les</WORD>
<WORD coords="1225,1696,1607,1627,1692">inventeurs</WORD>
<WORD coords="1634,1716,1652,1654,1716">;</WORD>
<WORD coords="1715,1694,1809,1626,1693">les</WORD>
<WORD coords="1863,1695,2193,1626,1693">honneurs</WORD>
<WORD coords="2264,1696,2339,1624,1696">&amp;</WORD>
</LINE>
<LINE>
<WORD coords="739,1854,803,1786,1854">le</WORD>
<WORD coords="849,1854,1090,1782,1851">mérite</WORD>
<WORD coords="1125,1852,1211,1783,1851">de</WORD>
<WORD coords="1251,1853,1519,1780,1851">l’aétion</WORD>
<WORD coords="1551,1877,2050,1788,1853">appartiennent</WORD>
<WORD coords="2080,1854,2161,1810,1853">au</WORD>
<WORD coords="2190,1877,2342,1799,1853">trop</WORD>
</LINE>
<LINE>
<WORD coords="741,2015,1011,1943,2012">célèbre</WORD>
<WORD coords="1063,2012,1301,1942,2010">Laclos</WORD>
<WORD coords="1339,2028,1361,1996,2032">,</WORD>
<WORD coords="1433,2038,1843,1942,2011">précepteur</WORD>
<WORD coords="1901,2011,1983,1967,2010">en</WORD>
<WORD coords="2038,2012,2197,1947,2011">titre</WORD>
<WORD coords="2265,2013,2341,1941,2013">&amp;</WORD>
</LINE>
<LINE>
<WORD coords="737,2175,1099,2105,2172">exécuteur</WORD>
<WORD coords="1154,2174,1234,2128,2173">en</WORD>
<WORD coords="1294,2171,1462,2100,2169">chef</WORD>
<WORD coords="1505,2173,1623,2102,2172">des</WORD>
<WORD coords="1702,2196,1945,2104,2171">projets</WORD>
<WORD coords="2020,2194,2334,2102,2170">régicides</WORD>
</LINE>
<LINE>
<WORD coords="739,2334,893,2262,2332">d’un</WORD>
<WORD coords="942,2329,1086,2264,2328">être</WORD>
<WORD coords="1124,2355,1323,2263,2329">qu’on</WORD>
<WORD coords="1356,2355,1682,2260,2328">qualifioit</WORD>
<WORD coords="1728,2355,1892,2262,2330">jadis</WORD>
<WORD coords="1929,2331,2014,2260,2330">de</WORD>
<WORD coords="2057,2350,2333,2262,2329">Prince,</WORD>
</LINE>
<LINE>
<WORD coords="745,2493,821,2420,2504">&amp;</WORD>
<WORD coords="865,2515,977,2426,2489">qui</WORD>
<WORD coords="999,2512,1017,2477,2512">,</WORD>
<WORD coords="1079,2489,1117,2420,2489">à</WORD>
<WORD coords="1160,2491,1315,2445,2489">mon</WORD>
<WORD coords="1352,2490,1484,2424,2488">avis</WORD>
<WORD coords="1531,2489,1621,2421,2488">eft</WORD>
<WORD coords="1674,2491,1894,2424,2489">même</WORD>
<WORD coords="1946,2514,2203,2420,2488">indigne</WORD>
<WORD coords="2256,2492,2343,2420,2490">du</WORD>
</LINE>
<LINE>
<WORD coords="745,2649,899,2602,2648">nom</WORD>
<WORD coords="946,2648,1300,2576,2647">d’homme.</WORD>
</LINE>
</PARAGRAPH>
<PARAGRAPH>
<LINE>
<WORD coords="1294,2879,1397,2821,2879">M.</WORD>
<WORD coords="1443,2879,1760,2818,2878">Richard.</WORD>
</LINE>
</PARAGRAPH>
<PARAGRAPH>
<LINE>
<WORD coords="846,3119,959,3047,3117">J’ai</WORD>
<WORD coords="985,3115,1067,3073,3115">en</WORD>
<WORD coords="1095,3116,1252,3048,3115">effet</WORD>
<WORD coords="1293,3118,1583,3048,3116">entendu</WORD>
<WORD coords="1615,3141,1828,3050,3116">parler</WORD>
<WORD coords="1874,3115,1957,3047,3114">de</WORD>
<WORD coords="1994,3114,2066,3070,3114">ce</WORD>
<WORD coords="2099,3115,2338,3045,3113">Laclos</WORD>
</LINE>
<LINE>
<WORD coords="751,3275,827,3204,3275">&amp;</WORD>
<WORD coords="864,3274,951,3204,3273">de</WORD>
<WORD coords="1001,3273,1109,3205,3271">fon</WORD>
<WORD coords="1151,3277,1355,3205,3273">Elève</WORD>
<WORD coords="1379,3294,1396,3260,3294">,</WORD>
<WORD coords="1446,3276,1604,3207,3273">mais</WORD>
<WORD coords="1666,3296,1729,3209,3272">je</WORD>
<WORD coords="1784,3296,2177,3203,3270">n’imaginois</WORD>
<WORD coords="2223,3296,2337,3228,3271">pas</WORD>
</LINE>
<LINE>
<WORD coords="755,3458,883,3389,3433">que</WORD>
<WORD coords="930,3435,1161,3362,3432">c’étoit</WORD>
<WORD coords="1200,3433,1235,3362,3433">à</WORD>
<WORD coords="1279,3433,1355,3388,3433">ce</WORD>
<WORD coords="1388,3458,1673,3362,3433">point-là</WORD>
<WORD coords="1700,3453,1721,3417,3457">,</WORD>
<WORD coords="1772,3457,1839,3365,3436">je</WORD>
<WORD coords="1886,3457,2138,3362,3431">penfois</WORD>
<WORD coords="2169,3458,2341,3361,3431">pref-</WORD>
</LINE>
</PARAGRAPH>
</REGION>
</PAGECOLUMN>
<PAGECOLUMN></PAGECOLUMN>
<PAGECOLUMN>
<REGION backgroundColor="15198170">
<PARAGRAPH>
<LINE>
<WORD coords="1464,3728,1490,3721,3728">__</WORD>
<WORD coords="1535,3728,1571,3698,3726">&lt;1</WORD>
</LINE>
</PARAGRAPH>
</REGION>
</PAGECOLUMN>
<PAGECOLUMN>
<REGION backgroundColor="15066584">
<PARAGRAPH>
<LINE>
<WORD coords="1368,3946,1430,3906,3946">&apos;*n</WORD>
<WORD coords="1436,3951,1540,3912,3948">ctff</WORD>
</LINE>
</PARAGRAPH>
</REGION>
</PAGECOLUMN>
</HIDDENTEXT>
</OBJECT>
<MAP name="cinquiemeconvers00unse_0002.djvu"/>
<OBJECT data="file://localhost//var/tmp/autoclean/derive/cinquiemeconvers00unse//cinquiemeconvers00unse.djvu" height="4335" type="image/x.djvu" usemap="cinquiemeconvers00unse_0003.djvu" width="2506">
<PARAM name="PAGE" value="cinquiemeconvers00unse_0003.djvu"/>
<PARAM name="DPI" value="500"/>
<HIDDENTEXT>
<PAGECOLUMN>
<REGION backgroundColor="15395026">
<PARAGRAPH>
<LINE>
<WORD coords="185,897,316,826,872">que</WORD>
<WORD coords="362,897,514,801,872">qu’il</WORD>
<WORD coords="552,896,598,828,896">y</WORD>
<WORD coords="633,873,811,804,870">avoit</WORD>
<WORD coords="855,870,940,800,869">de</WORD>
<WORD coords="996,871,1057,803,870">la</WORD>
<WORD coords="1086,872,1407,801,869">calomnie</WORD>
<WORD coords="1455,869,1597,799,868">fous</WORD>
<WORD coords="1638,889,1779,801,869">jeu;</WORD>
</LINE>
<LINE>
<WORD coords="186,1032,344,966,1031">mais</WORD>
<WORD coords="398,1057,664,962,1031">puifque</WORD>
<WORD coords="727,1029,889,985,1028">vous</WORD>
<WORD coords="945,1029,1052,985,1029">me</WORD>
<WORD coords="1095,1028,1156,961,1027">le</WORD>
<WORD coords="1224,1045,1436,960,1028">dites,</WORD>
<WORD coords="1502,1052,1563,963,1027">je</WORD>
<WORD coords="1608,1030,1781,960,1029">m’en</WORD>
</LINE>
<LINE>
<WORD coords="184,1215,497,1137,1189">rapporte</WORD>
<WORD coords="528,1190,563,1120,1191">à</WORD>
<WORD coords="588,1208,782,1145,1189">vous,</WORD>
<WORD coords="827,1214,1027,1144,1188">parce</WORD>
<WORD coords="1059,1214,1188,1144,1185">que</WORD>
<WORD coords="1222,1211,1284,1121,1185">je</WORD>
<WORD coords="1313,1190,1473,1143,1187">vous</WORD>
<WORD coords="1508,1189,1778,1121,1187">connois</WORD>
</LINE>
<LINE>
<WORD coords="185,1350,258,1280,1361">&amp;</WORD>
<WORD coords="302,1372,364,1283,1347">je</WORD>
<WORD coords="402,1348,513,1280,1346">fais</WORD>
<WORD coords="559,1348,887,1278,1346">d’ailleurs</WORD>
<WORD coords="928,1372,1057,1304,1345">que</WORD>
<WORD coords="1100,1345,1258,1303,1345">vous</WORD>
<WORD coords="1293,1347,1638,1276,1345">n’avancez</WORD>
<WORD coords="1682,1368,1776,1280,1347">ja-</WORD>
</LINE>
<LINE>
<WORD coords="182,1507,337,1443,1506">mais</WORD>
<WORD coords="364,1507,451,1465,1506">un</WORD>
<WORD coords="485,1507,605,1435,1505">fait</WORD>
<WORD coords="629,1529,646,1493,1529">,</WORD>
<WORD coords="687,1506,818,1438,1505">fans</WORD>
<WORD coords="845,1531,1125,1443,1506">pouvoir</WORD>
<WORD coords="1149,1508,1401,1436,1506">fournir</WORD>
<WORD coords="1432,1508,1490,1440,1507">la</WORD>
<WORD coords="1522,1532,1776,1460,1508">preuve</WORD>
</LINE>
<LINE>
<WORD coords="180,1688,654,1594,1663">fur-le-champ.</WORD>
</LINE>
</PARAGRAPH>
<PARAGRAPH>
<LINE>
<WORD coords="760,1875,861,1819,1875">M.</WORD>
<WORD coords="930,1877,1216,1817,1875">Courtois</WORD>
<WORD coords="1218,1877,1240,1860,1877">*</WORD>
</LINE>
</PARAGRAPH>
<PARAGRAPH>
<LINE>
<WORD coords="273,2096,456,2029,2094">Vous</WORD>
<WORD coords="511,2100,671,2052,2096">avez</WORD>
<WORD coords="705,2114,947,2029,2095">raifon;</WORD>
<WORD coords="982,2095,1133,2025,2094">aufïi</WORD>
<WORD coords="1156,2119,1216,2031,2093">je</WORD>
<WORD coords="1244,2099,1375,2032,2096">vais</WORD>
<WORD coords="1416,2096,1578,2050,2094">vous</WORD>
<WORD coords="1612,2097,1772,2025,2095">don-</WORD>
</LINE>
<LINE>
<WORD coords="175,2254,292,2210,2252">ner</WORD>
<WORD coords="316,2255,409,2186,2253">les</WORD>
<WORD coords="434,2278,714,2211,2254">preuves</WORD>
<WORD coords="749,2279,998,2184,2254">d’après</WORD>
<WORD coords="1028,2280,1370,2185,2253">lefquelles</WORD>
<WORD coords="1412,2275,1473,2187,2252">je</WORD>
<WORD coords="1509,2254,1617,2211,2253">me</WORD>
<WORD coords="1648,2256,1772,2183,2253">fuis</WORD>
</LINE>
<LINE>
<WORD coords="186,2413,428,2344,2409">avancé</WORD>
<WORD coords="489,2410,551,2344,2409">le</WORD>
<WORD coords="595,2432,743,2342,2410">jour</WORD>
<WORD coords="793,2412,882,2344,2412">du</WORD>
<WORD coords="935,2438,1170,2358,2412">tapage</WORD>
<WORD coords="1220,2414,1347,2368,2413">aux</WORD>
<WORD coords="1396,2414,1775,2343,2411">Thuileries</WORD>
</LINE>
<LINE>
<WORD coords="173,2594,340,2527,2569">pour</WORD>
<WORD coords="394,2570,456,2504,2569">le</WORD>
<WORD coords="515,2596,751,2502,2569">départ</WORD>
<WORD coords="807,2570,895,2501,2570">du</WORD>
<WORD coords="961,2572,1105,2503,2571">Roi.</WORD>
<WORD coords="1164,2572,1278,2502,2571">J’ai</WORD>
<WORD coords="1334,2571,1422,2527,2570">vu</WORD>
<WORD coords="1467,2570,1562,2501,2568">les</WORD>
<WORD coords="1619,2592,1772,2526,2568">gens</WORD>
</LINE>
<LINE>
<WORD coords="172,2729,519,2658,2727">d&apos;Orléans</WORD>
<WORD coords="543,2750,557,2716,2750">,</WORD>
<WORD coords="603,2732,678,2659,2732">&amp;</WORD>
<WORD coords="738,2731,841,2660,2729">M.</WORD>
<WORD coords="892,2730,1129,2660,2728">Laclos</WORD>
<WORD coords="1172,2729,1206,2660,2729">à</WORD>
<WORD coords="1240,2727,1388,2660,2726">leur</WORD>
<WORD coords="1435,2727,1572,2662,2726">tête</WORD>
<WORD coords="1596,2746,1614,2711,2746">,</WORD>
<WORD coords="1662,2728,1777,2684,2727">ex-</WORD>
</LINE>
<LINE>
<WORD coords="168,2885,339,2818,2883">citer</WORD>
<WORD coords="387,2886,448,2818,2885">la</WORD>
<WORD coords="510,2910,836,2817,2883">populace</WORD>
<WORD coords="890,2886,963,2814,2886">&amp;</WORD>
<WORD coords="1012,2887,1278,2815,2885">faufiler</WORD>
<WORD coords="1329,2885,1387,2817,2885">la</WORD>
<WORD coords="1456,2901,1773,2814,2884">fédition;</WORD>
</LINE>
<LINE>
<WORD coords="162,3065,266,2973,3041">j’ai</WORD>
<WORD coords="314,3046,402,3000,3044">vu</WORD>
<WORD coords="451,3043,545,2975,3042">les</WORD>
<WORD coords="587,3043,909,2978,3042">courriers</WORD>
<WORD coords="951,3043,1108,2974,3041">aller</WORD>
<WORD coords="1145,3044,1220,2973,3045">&amp;</WORD>
<WORD coords="1272,3046,1456,2976,3042">venir</WORD>
<WORD coords="1516,3042,1601,2974,3042">du</WORD>
<WORD coords="1661,3044,1778,2977,3043">Pa-</WORD>
</LINE>
<LINE>
<WORD coords="166,3228,546,3134,3202">lais-Royal</WORD>
<WORD coords="566,3202,647,3160,3201">au</WORD>
<WORD coords="678,3203,1010,3132,3201">Carouzel</WORD>
<WORD coords="1031,3222,1049,3188,3223">,</WORD>
<WORD coords="1087,3224,1350,3147,3201">portant</WORD>
<WORD coords="1396,3202,1489,3134,3200">les</WORD>
<WORD coords="1534,3202,1765,3132,3200">ordres</WORD>
</LINE>
<LINE>
<WORD coords="172,3361,246,3290,3361">&amp;</WORD>
<WORD coords="286,3383,658,3305,3358">annonçant</WORD>
<WORD coords="696,3360,773,3318,3359">au</WORD>
<WORD coords="807,3382,1218,3293,3361">Bourjëonné</WORD>
<WORD coords="1257,3388,1369,3298,3361">qui</WORD>
<WORD coords="1406,3364,1502,3293,3362">lés</WORD>
<WORD coords="1542,3363,1771,3307,3362">atten-</WORD>
</LINE>
<LINE>
<WORD coords="174,3537,348,3447,3515">dait,</WORD>
<WORD coords="413,3518,509,3449,3516">les</WORD>
<WORD coords="562,3519,789,3449,3517">détails</WORD>
<WORD coords="839,3518,872,3448,3518">à</WORD>
<WORD coords="925,3522,1182,3450,3520">mefure</WORD>
<WORD coords="1247,3545,1433,3450,3518">qu’ils</WORD>
<WORD coords="1482,3521,1771,3449,3519">s’exécu-</WORD>
</LINE>
</PARAGRAPH>
</REGION>
</PAGECOLUMN>
</HIDDENTEXT>
</OBJECT>
<MAP name="cinquiemeconvers00unse_0003.djvu"/>
<OBJECT data="file://localhost//var/tmp/autoclean/derive/cinquiemeconvers00unse//cinquiemeconvers00unse.djvu" height="4335" type="image/x.djvu" usemap="cinquiemeconvers00unse_0004.djvu" width="2506">
<PARAM name="PAGE" value="cinquiemeconvers00unse_0004.djvu"/>
<PARAM name="DPI" value="500"/>
<HIDDENTEXT>
<PAGECOLUMN>
<REGION backgroundColor="15329746">
<PARAGRAPH>
<LINE>
<WORD coords="1375,663,1413,561,663">(</WORD>
<WORD coords="1465,651,1507,589,651">4</WORD>
<WORD coords="1555,659,1593,561,659">)</WORD>
</LINE>
</PARAGRAPH>
<PARAGRAPH>
<LINE>
<WORD coords="687,811,918,742,809">toient.</WORD>
<WORD coords="969,809,1070,738,808">Ce</WORD>
<WORD coords="1103,833,1229,763,807">que</WORD>
<WORD coords="1256,830,1361,737,815">fai</WORD>
<WORD coords="1401,809,1503,739,807">dit</WORD>
<WORD coords="1528,830,1545,796,830">,</WORD>
<WORD coords="1587,829,1649,739,808">je</WORD>
<WORD coords="1685,810,1791,740,809">Fai</WORD>
<WORD coords="1824,810,1929,765,809">vu.</WORD>
<WORD coords="1963,812,2076,739,811">Pai</WORD>
<WORD coords="2100,836,2275,743,812">paffié</WORD>
</LINE>
<LINE>
<WORD coords="685,992,921,900,967">exprès</WORD>
<WORD coords="969,968,1028,900,967">la</WORD>
<WORD coords="1067,989,1338,899,965">journée</WORD>
<WORD coords="1378,967,1467,897,966">du</WORD>
<WORD coords="1500,968,1687,898,967">lundi</WORD>
<WORD coords="1720,969,1799,924,968">au</WORD>
<WORD coords="1834,971,2161,899,969">Carouzel</WORD>
<WORD coords="2202,973,2280,902,973">&amp;</WORD>
</LINE>
<LINE>
<WORD coords="687,1125,770,1081,1124">au</WORD>
<WORD coords="820,1151,1294,1056,1125">Palais-Royal</WORD>
<WORD coords="1324,1149,1342,1088,1149">;</WORD>
<WORD coords="1393,1150,1495,1060,1126">j’ai</WORD>
<WORD coords="1535,1128,1621,1085,1127">vu</WORD>
<WORD coords="1661,1130,1755,1059,1128">les</WORD>
<WORD coords="1809,1153,2067,1061,1128">lignaux</WORD>
<WORD coords="2091,1150,2107,1116,1150">,</WORD>
<WORD coords="2177,1150,2282,1059,1128">j’ai</WORD>
</LINE>
<LINE>
<WORD coords="688,1288,776,1239,1285">vu</WORD>
<WORD coords="802,1283,894,1218,1283">les</WORD>
<WORD coords="923,1311,1361,1215,1285">domeltiques</WORD>
<WORD coords="1387,1288,1617,1217,1287">affidés</WORD>
<WORD coords="1644,1287,1731,1218,1287">du</WORD>
<WORD coords="1753,1312,2042,1219,1287">régicide</WORD>
<WORD coords="2070,1289,2281,1219,1287">d’Or-</WORD>
</LINE>
<LINE>
<WORD coords="688,1444,865,1373,1442">léans</WORD>
<WORD coords="881,1461,898,1427,1461">3</WORD>
<WORD coords="941,1443,1003,1375,1443">fe</WORD>
<WORD coords="1042,1445,1292,1377,1443">mêlant</WORD>
<WORD coords="1344,1446,1499,1376,1444">dans</WORD>
<WORD coords="1546,1445,1638,1376,1444">les</WORD>
<WORD coords="1684,1470,1966,1401,1444">groupes</WORD>
<WORD coords="2011,1445,2097,1375,1444">de</WORD>
<WORD coords="2134,1445,2286,1375,1442">fcé-</WORD>
</LINE>
<LINE>
<WORD coords="689,1603,893,1530,1602">lérats</WORD>
<WORD coords="941,1627,1053,1538,1602">qui</WORD>
<WORD coords="1105,1604,1538,1533,1603">s’afïemblent</WORD>
<WORD coords="1590,1603,1668,1562,1603">au</WORD>
<WORD coords="1702,1606,1902,1537,1603">Palais</WORD>
<WORD coords="1946,1630,2178,1535,1602">royal;</WORD>
<WORD coords="2221,1627,2290,1535,1600">je</WORD>
</LINE>
<LINE>
<WORD coords="694,1762,793,1692,1761">les</WORD>
<WORD coords="843,1762,900,1698,1762">ai</WORD>
<WORD coords="950,1763,1245,1695,1762">entendu</WORD>
<WORD coords="1307,1764,1680,1694,1763">déclamant</WORD>
<WORD coords="1736,1763,1968,1709,1762">contre</WORD>
<WORD coords="2020,1762,2082,1695,1761">la</WORD>
<WORD coords="2136,1785,2292,1718,1759">per-i</WORD>
</LINE>
</PARAGRAPH>
<PARAGRAPH>
<LINE>
<WORD coords="2057,1822,2071,1794,1822">V</WORD>
</LINE>
</PARAGRAPH>
<PARAGRAPH>
<LINE>
<WORD coords="695,1922,893,1853,1921">fonne</WORD>
<WORD coords="952,1923,1043,1853,1922">du</WORD>
<WORD coords="1106,1924,1241,1855,1922">Roi</WORD>
<WORD coords="1311,1924,1425,1854,1923">des</WORD>
<WORD coords="1469,1925,1777,1855,1923">horreurs</WORD>
<WORD coords="1824,1924,1987,1854,1922">dont</WORD>
<WORD coords="2059,1923,2141,1880,1922">on</WORD>
<WORD coords="2204,1921,2287,1878,1921">ne</WORD>
</LINE>
<LINE>
<WORD coords="697,2106,872,2026,2078">peut</WORD>
<WORD coords="908,2080,968,2013,2079">fe</WORD>
<WORD coords="993,2081,1246,2009,2080">former</WORD>
<WORD coords="1289,2083,1532,2009,2081">d’idées</WORD>
<WORD coords="1562,2102,1580,2069,2102">,</WORD>
<WORD coords="1616,2083,1691,2011,2094">&amp;</WORD>
<WORD coords="1725,2106,1852,2038,2079">que</WORD>
<WORD coords="1882,2103,1944,2016,2078">je</WORD>
<WORD coords="1980,2079,2060,2037,2078">ne</WORD>
<WORD coords="2084,2103,2287,2035,2076">pour-</WORD>
</LINE>
<LINE>
<WORD coords="694,2238,831,2170,2236">rois</WORD>
<WORD coords="879,2264,1197,2169,2238">répéter,</WORD>
<WORD coords="1251,2266,1667,2171,2239">puifqu’elles</WORD>
<WORD coords="1719,2242,2002,2168,2240">feroient</WORD>
<WORD coords="2057,2242,2287,2168,2238">frémir</WORD>
</LINE>
<LINE>
<WORD coords="694,2398,790,2328,2397">les</WORD>
<WORD coords="835,2400,1151,2328,2398">honnêtes</WORD>
<WORD coords="1187,2427,1363,2354,2398">gens,</WORD>
</LINE>
</PARAGRAPH>
<PARAGRAPH>
<LINE>
<WORD coords="1252,2612,1354,2555,2612">M.</WORD>
<WORD coords="1394,2612,1711,2551,2611">Richard.</WORD>
</LINE>
</PARAGRAPH>
<PARAGRAPH>
<LINE>
<WORD coords="797,2831,905,2763,2829">Ce</WORD>
<WORD coords="942,2854,1075,2785,2829">que</WORD>
<WORD coords="1123,2830,1284,2784,2829">vous</WORD>
<WORD coords="1333,2829,1441,2786,2828">me</WORD>
<WORD coords="1483,2831,1701,2758,2829">dites-</WORD>
<WORD coords="1724,2829,1788,2758,2829">là</WORD>
<WORD coords="1827,2829,1916,2756,2828">eft</WORD>
<WORD coords="1963,2846,2131,2762,2829">vrai;</WORD>
<WORD coords="2189,2848,2291,2757,2833">fai</WORD>
</LINE>
<LINE>
<WORD coords="702,2990,813,2919,2988">été</WORD>
<WORD coords="835,2990,1084,2919,2987">témoin</WORD>
<WORD coords="1114,2988,1306,2917,2987">d’üne</WORD>
<WORD coords="1339,3013,1552,2925,2987">partie</WORD>
<WORD coords="1573,3007,1589,2975,3007">,</WORD>
<WORD coords="1628,2988,1786,2922,2987">mais</WORD>
<WORD coords="1827,2988,1979,2917,2987">auffi</WORD>
<WORD coords="2013,2986,2104,2918,2985">les</WORD>
<WORD coords="2126,2989,2294,2916,2986">voilà</WORD>
</LINE>
<LINE>
<WORD coords="698,3148,856,3079,3147">bien</WORD>
<WORD coords="900,3169,1195,3078,3147">déjoués.</WORD>
<WORD coords="1249,3148,1350,3078,3147">La</WORD>
<WORD coords="1391,3151,1616,3078,3148">Garde</WORD>
<WORD coords="1664,3147,1983,3078,3146">nationale</WORD>
<WORD coords="2041,3148,2128,3076,3147">eft</WORD>
<WORD coords="2176,3148,2294,3105,3148">re-</WORD>
</LINE>
<LINE>
<WORD coords="702,3310,915,3261,3306">venue</WORD>
<WORD coords="958,3306,1043,3236,3305">de</WORD>
<WORD coords="1087,3307,1199,3238,3306">fon</WORD>
<WORD coords="1241,3324,1500,3262,3308">erreur,</WORD>
<WORD coords="1545,3309,1619,3238,3309">&amp;</WORD>
<WORD coords="1650,3307,1724,3236,3306">ils</WORD>
<WORD coords="1759,3307,1977,3236,3305">feront</WORD>
<WORD coords="2016,3309,2167,3236,3306">bien</WORD>
<WORD coords="2208,3305,2294,3236,3305">de</WORD>
</LINE>
<LINE>
<WORD coords="706,3469,786,3422,3468">ne</WORD>
<WORD coords="829,3492,932,3400,3467">s*y</WORD>
<WORD coords="972,3491,1114,3398,3467">plus</WORD>
<WORD coords="1160,3469,1421,3393,3466">frotter,</WORD>
</LINE>
</PARAGRAPH>
<PARAGRAPH>
<LINE>
<WORD coords="780,3734,782,3732,3745">■</WORD>
<WORD coords="825,3757,856,3723,3757">\</WORD>
<WORD coords="1052,3727,1056,3723,3731">&apos;</WORD>
<WORD coords="1896,3736,1904,3733,3736">-</WORD>
</LINE>
</PARAGRAPH>
</REGION>
</PAGECOLUMN>
<PAGECOLUMN>
<REGION backgroundColor="15263956">
<PARAGRAPH>
<LINE>
<WORD coords="1196,3858,1203,3830,3858">i</WORD>
</LINE>
</PARAGRAPH>
</REGION>
</PAGECOLUMN>
</HIDDENTEXT>
</OBJECT>
<MAP name="cinquiemeconvers00unse_0004.djvu"/>
<OBJECT data="file://localhost//var/tmp/autoclean/derive/cinquiemeconvers00unse//cinquiemeconvers00unse.djvu" height="4335" type="image/x.djvu" usemap="cinquiemeconvers00unse_0005.djvu" width="2506">
<PARAM name="PAGE" value="cinquiemeconvers00unse_0005.djvu"/>
<PARAM name="DPI" value="500"/>
<HIDDENTEXT>
<PAGECOLUMN>
<REGION backgroundColor="15066318">
<PARAGRAPH>
<LINE>
<WORD coords="775,858,859,802,858">M.</WORD>
<WORD coords="926,858,1218,797,856">Courtois</WORD>
<WORD coords="1223,854,1238,840,854">.</WORD>
</LINE>
</PARAGRAPH>
</REGION>
</PAGECOLUMN>
<PAGECOLUMN>
<REGION backgroundColor="15197906">
<PARAGRAPH>
<LINE>
<WORD coords="294,1037,482,966,1035">Vous</WORD>
<WORD coords="526,1039,685,989,1035">avez</WORD>
<WORD coords="751,1055,994,965,1033">raifon;</WORD>
<WORD coords="1037,1034,1099,966,1033">la</WORD>
<WORD coords="1156,1034,1383,960,1032">Garde</WORD>
<WORD coords="1441,1031,1531,958,1030">eft</WORD>
<WORD coords="1597,1033,1793,982,1030">reve-</WORD>
</LINE>
<LINE>
<WORD coords="198,1194,327,1149,1193">nue</WORD>
<WORD coords="348,1214,366,1178,1214">5</WORD>
<WORD coords="414,1193,540,1125,1191">elle</WORD>
<WORD coords="582,1193,672,1121,1193">eft</WORD>
<WORD coords="701,1194,959,1124,1191">rentrée</WORD>
<WORD coords="1003,1192,1158,1122,1191">dans</WORD>
<WORD coords="1201,1190,1265,1121,1189">le</WORD>
<WORD coords="1314,1190,1546,1118,1188">devoir</WORD>
<WORD coords="1569,1210,1589,1147,1210">;</WORD>
<WORD coords="1633,1187,1795,1118,1186">mais</WORD>
</LINE>
<LINE>
<WORD coords="195,1353,355,1305,1349">avec</WORD>
<WORD coords="409,1375,627,1280,1348">quelle</WORD>
<WORD coords="670,1351,883,1280,1349">aftuce</WORD>
<WORD coords="908,1369,926,1335,1369">,</WORD>
<WORD coords="987,1351,1147,1302,1348">avec</WORD>
<WORD coords="1188,1373,1408,1276,1345">quelle</WORD>
<WORD coords="1460,1344,1798,1273,1342">fourberie</WORD>
</LINE>
<LINE>
<WORD coords="199,1507,283,1464,1506">on</WORD>
<WORD coords="326,1510,608,1439,1508">cherche</WORD>
<WORD coords="651,1529,802,1440,1511">déjà</WORD>
<WORD coords="855,1510,891,1440,1510">à</WORD>
<WORD coords="930,1509,988,1439,1508">la</WORD>
<WORD coords="1034,1510,1340,1439,1506">foulever.</WORD>
<WORD coords="1391,1506,1577,1436,1503">Vous</WORD>
<WORD coords="1612,1504,1799,1434,1503">favez</WORD>
</LINE>
<LINE>
<WORD coords="209,1694,339,1624,1667">que</WORD>
<WORD coords="392,1668,486,1599,1667">les</WORD>
<WORD coords="542,1668,945,1598,1666">Grenadiers</WORD>
<WORD coords="1005,1667,1218,1597,1665">foldés</WORD>
<WORD coords="1252,1665,1258,1658,1665">.</WORD>
<WORD coords="1292,1666,1375,1595,1665">de</WORD>
<WORD coords="1430,1669,1801,1594,1663">l’Oratoire</WORD>
</LINE>
<LINE>
<WORD coords="205,1824,320,1769,1822">ont</WORD>
<WORD coords="350,1824,459,1755,1824">été</WORD>
<WORD coords="486,1826,786,1757,1823">licenciés</WORD>
<WORD coords="812,1849,930,1781,1823">par</WORD>
<WORD coords="956,1824,1015,1756,1823">la</WORD>
<WORD coords="1042,1824,1419,1753,1822">Commune</WORD>
<WORD coords="1446,1843,1464,1781,1843">;</WORD>
<WORD coords="1495,1821,1579,1752,1820">eh</WORD>
<WORD coords="1605,1820,1761,1752,1820">bien</WORD>
<WORD coords="1782,1821,1798,1750,1821">!</WORD>
</LINE>
<LINE>
<WORD coords="199,1983,343,1913,1981">hier</WORD>
<WORD coords="368,2002,385,1968,2002">,</WORD>
<WORD coords="429,1982,585,1913,1982">dans</WORD>
<WORD coords="634,1983,696,1913,1981">le</WORD>
<WORD coords="737,2009,1198,1913,1982">Palais-Royal</WORD>
<WORD coords="1245,1985,1319,1913,1985">&amp;</WORD>
<WORD coords="1346,1983,1504,1913,1981">dans</WORD>
<WORD coords="1535,1982,1682,1926,1981">tous</WORD>
<WORD coords="1707,1981,1801,1912,1980">les</WORD>
</LINE>
<LINE>
<WORD coords="200,2143,379,2074,2142">lieux</WORD>
<WORD coords="445,2167,699,2074,2141">publics</WORD>
<WORD coords="760,2143,846,2098,2142">on</WORD>
<WORD coords="901,2143,1110,2072,2142">faifoit</WORD>
<WORD coords="1163,2141,1334,2076,2140">crier</WORD>
<WORD coords="1400,2140,1493,2072,2139">les</WORD>
<WORD coords="1554,2165,1710,2096,2139">gens</WORD>
<WORD coords="1768,2139,1805,2068,2139">à</WORD>
</LINE>
<LINE>
<WORD coords="202,2327,518,2246,2300">quarante</WORD>
<WORD coords="563,2301,703,2232,2300">fous</WORD>
<WORD coords="738,2324,853,2257,2299">par</WORD>
<WORD coords="906,2323,1092,2233,2299">jour,</WORD>
<WORD coords="1144,2300,1375,2243,2298">contre</WORD>
<WORD coords="1409,2299,1470,2232,2298">le</WORD>
<WORD coords="1505,2303,1808,2229,2300">Général</WORD>
</LINE>
</PARAGRAPH>
<PARAGRAPH>
<LINE>
<WORD coords="206,2459,281,2388,2459">&amp;</WORD>
<WORD coords="318,2457,376,2388,2455">la</WORD>
<WORD coords="417,2483,912,2390,2457">Municipalité,</WORD>
<WORD coords="956,2483,1157,2414,2457">parce</WORD>
<WORD coords="1193,2483,1321,2415,2458">que</WORD>
<WORD coords="1352,2458,1483,2388,2457">l’un</WORD>
<WORD coords="1511,2460,1807,2391,2458">exécute</WORD>
</LINE>
<LINE>
<WORD coords="213,2594,308,2525,2593">les</WORD>
<WORD coords="359,2597,585,2526,2595">ordres</WORD>
<WORD coords="635,2622,764,2553,2596">que</WORD>
<WORD coords="808,2597,1034,2525,2595">l’autre</WORD>
<WORD coords="1079,2596,1114,2553,2596">a</WORD>
<WORD coords="1145,2599,1412,2527,2596">donnés.</WORD>
</LINE>
</PARAGRAPH>
<PARAGRAPH>
<LINE>
<WORD coords="777,2763,879,2707,2763">M.</WORD>
<WORD coords="951,2765,1260,2704,2764">Richard</WORD>
<WORD coords="1260,2764,1271,2752,2764">.</WORD>
</LINE>
</PARAGRAPH>
<PARAGRAPH>
<LINE>
<WORD coords="307,2943,383,2873,2942">Je</WORD>
<WORD coords="450,2943,620,2875,2941">crois</WORD>
<WORD coords="681,2968,811,2900,2942">que</WORD>
<WORD coords="874,2967,1042,2899,2943">pour</WORD>
<WORD coords="1102,2944,1180,2899,2943">ce</WORD>
<WORD coords="1240,2967,1413,2899,2944">coup</WORD>
<WORD coords="1463,2945,1545,2876,2943">ici</WORD>
<WORD coords="1587,2945,1663,2874,2942">ils</WORD>
<WORD coords="1727,2946,1812,2900,2945">ne</WORD>
</LINE>
<LINE>
<WORD coords="228,3101,575,3030,3099">réuffiront</WORD>
<WORD coords="614,3124,745,3057,3101">pas.</WORD>
</LINE>
</PARAGRAPH>
<PARAGRAPH>
<LINE>
<WORD coords="759,3269,862,3211,3267">M.</WORD>
<WORD coords="918,3270,1211,3210,3269">Courtois</WORD>
<WORD coords="1217,3272,1244,3224,0">2</WORD>
</LINE>
</PARAGRAPH>
<PARAGRAPH>
<LINE>
<WORD coords="304,3445,378,3375,3443">Je</WORD>
<WORD coords="416,3470,679,3374,3444">l’efpère</WORD>
<WORD coords="706,3466,724,3405,3466">;</WORD>
<WORD coords="775,3446,930,3381,3445">mais</WORD>
<WORD coords="998,3448,1171,3378,3447">enfin</WORD>
<WORD coords="1227,3448,1374,3392,3447">tout</WORD>
<WORD coords="1439,3449,1579,3381,3447">cela</WORD>
<WORD coords="1649,3452,1814,3404,3449">nous</WORD>
</LINE>
<LINE>
<WORD coords="212,3587,562,3513,3585">démontre</WORD>
<WORD coords="628,3588,783,3518,3586">bien</WORD>
<WORD coords="848,3594,1300,3518,3590">évidemment</WORD>
<WORD coords="1379,3614,1567,3518,3587">qu’ils</WORD>
<WORD coords="1634,3590,1814,3517,3589">n’ont</WORD>
</LINE>
</PARAGRAPH>
</REGION>
</PAGECOLUMN>
</HIDDENTEXT>
</OBJECT>
<MAP name="cinquiemeconvers00unse_0005.djvu"/>
<OBJECT data="file://localhost//var/tmp/autoclean/derive/cinquiemeconvers00unse//cinquiemeconvers00unse.djvu" height="4335" type="image/x.djvu" usemap="cinquiemeconvers00unse_0006.djvu" width="2506">
<PARAM name="PAGE" value="cinquiemeconvers00unse_0006.djvu"/>
<PARAM name="DPI" value="500"/>
<HIDDENTEXT>
<PAGECOLUMN>
<REGION backgroundColor="15263701">
<PARAGRAPH>
<LINE>
<WORD coords="1374,678,1410,586,678">C</WORD>
<WORD coords="1466,654,1506,582,668">6</WORD>
<WORD coords="1558,682,1590,586,682">)</WORD>
</LINE>
</PARAGRAPH>
<PARAGRAPH>
<LINE>
<WORD coords="687,843,803,772,817">pas</WORD>
<WORD coords="850,818,1134,748,816">renoncé</WORD>
<WORD coords="1191,815,1227,745,815">à</WORD>
<WORD coords="1277,819,1452,747,816">leurs</WORD>
<WORD coords="1532,845,1825,749,815">projets;</WORD>
<WORD coords="1895,817,1974,773,817">au</WORD>
<WORD coords="2029,842,2282,748,816">fiirplus</WORD>
</LINE>
<LINE>
<WORD coords="687,994,944,906,975">j’arrive</WORD>
<WORD coords="965,997,984,964,999">,</WORD>
<WORD coords="1058,999,1120,910,975">je</WORD>
<WORD coords="1185,984,1322,904,979">vais</WORD>
<WORD coords="1391,978,1609,913,977">courir</WORD>
<WORD coords="1665,977,1759,908,975">les</WORD>
<WORD coords="1823,1002,2137,933,976">groupes,</WORD>
<WORD coords="2210,978,2285,906,978">&amp;</WORD>
</LINE>
<LINE>
<WORD coords="687,1137,732,1065,1137">fi</WORD>
<WORD coords="797,1156,1115,1064,1134">j’entends</WORD>
<WORD coords="1187,1161,1472,1069,1134">quelque</WORD>
<WORD coords="1541,1137,1726,1068,1134">choie</WORD>
<WORD coords="1792,1160,1903,1069,1133">qui</WORD>
<WORD coords="1968,1136,2157,1068,1134">vaille</WORD>
<WORD coords="2224,1134,2284,1067,1134">ia</WORD>
</LINE>
<LINE>
<WORD coords="688,1319,887,1228,1292">peine</WORD>
<WORD coords="953,1294,1162,1225,1293">d’être</WORD>
<WORD coords="1239,1294,1478,1240,1293">retenu</WORD>
<WORD coords="1503,1311,1524,1283,1318">,</WORD>
<WORD coords="1593,1318,1654,1229,1293">je</WORD>
<WORD coords="1736,1294,1899,1251,1293">vous</WORD>
<WORD coords="1988,1318,2288,1239,1292">promets</WORD>
</LINE>
<LINE>
<WORD coords="687,1453,774,1384,1452">de</WORD>
<WORD coords="841,1453,904,1384,1452">le</WORD>
<WORD coords="954,1455,1112,1381,1452">faire</WORD>
<WORD coords="1170,1478,1513,1387,1452">imprimer</WORD>
<WORD coords="1577,1478,1744,1411,1455">pour</WORD>
<WORD coords="1801,1455,1961,1383,1453">faire</WORD>
<WORD coords="2005,1478,2285,1385,1452">déjouer</WORD>
</LINE>
<LINE>
<WORD coords="691,1613,799,1568,1612">ces</WORD>
<WORD coords="858,1614,1221,1542,1611">Meilleurs.</WORD>
</LINE>
</PARAGRAPH>
</REGION>
</PAGECOLUMN>
</HIDDENTEXT>
</OBJECT>
<MAP name="cinquiemeconvers00unse_0006.djvu"/>
</BODY>
</DjVuXML>
